shadb.py
shadb-0.1.0.dist-info/METADATA
shadb-0.1.0.dist-info/WHEEL
shadb-0.1.0.dist-info/top_level.txt
shadb-0.1.0.dist-info/RECORD
